synapse/__init__.py
synapse/__version__.py
synapse/alert.py
synapse/bcolors.py
synapse/callback.py
synapse/log.py
synapse/stypes.py
synapse/util.py
synapse/core/__init__.py
synapse/core/camera_factory.py
synapse/core/camera_handler.py
synapse/core/config.py
synapse/core/global_settings.py
synapse/core/nt_keys.py
synapse/core/pipeline.py
synapse/core/pipeline_handler.py
synapse/core/results_api.py
synapse/core/runtime_handler.py
synapse/core/settings_api.py
synapse/core/synapse.py
synapse/hardware/__init__.py
synapse/hardware/deviceactions.py
synapse/hardware/metrics.py
synapse/pipelines/__init__.py
synapse/pipelines/color_pipeline.py
synapse/pipelines/apriltag/__init__.py
synapse/pipelines/apriltag/apriltag_detector.py
synapse/pipelines/apriltag/apriltag_pipeline.py
synapse/pipelines/apriltag/apriltag_robotpy.py
synapse/pipelines/apriltag/field_loader.py
synapse/pipelines/apriltag/multi_tag_estimator.py
synapse/pipelines/system/__init__.py
synapse/pipelines/system/calibration_pipeline.py
synapse/pipelines/system/driver_pipeline.py
synapse_installer/__init__.py
synapse_installer/__main__.py
synapse_installer/command_executor.py
synapse_installer/create.py
synapse_installer/deploy.py
synapse_installer/lockfile.py
synapse_installer/setup_service.py
synapse_installer/sync.py
synapse_installer/util.py
synapse_net/__init__.py
synapse_net/devicenetworking.py
synapse_net/file_server.py
synapse_net/nt_client.py
synapse_net/socketServer.py
synapse_net/ui_handle.py
synapse_net/proto/__init__.py
synapse_net/proto/settings/__init__.py
synapse_net/proto/settings/v1/__init__.py
synapse_net/proto/v1/__init__.py
synapse_ui/404.html
synapse_ui/__init__.py
synapse_ui/camera.html
synapse_ui/camera.txt
synapse_ui/dashboard.html
synapse_ui/dashboard.txt
synapse_ui/favicon.ico
synapse_ui/file.svg
synapse_ui/globe.svg
synapse_ui/index.html
synapse_ui/index.txt
synapse_ui/next.svg
synapse_ui/settings.html
synapse_ui/settings.txt
synapse_ui/vercel.svg
synapse_ui/window.svg
synapsefrc-2026.0.0a1.dist-info/licenses/LICENSE
synapsefrc-2026.0.0a1.dist-info/METADATA
synapsefrc-2026.0.0a1.dist-info/WHEEL
synapsefrc-2026.0.0a1.dist-info/entry_points.txt
synapsefrc-2026.0.0a1.dist-info/top_level.txt
synapsefrc-2026.0.0a1.dist-info/RECORD
