Metadata-Version: 2.4
Name: synapsefrc
Version: 2026.0.0a1
Summary: Dynamic vision processing system for FRC coprocessors
Requires-Python: >=3.11, <=3.14
License-File: LICENSE
Requires-Dist: rich
Requires-Dist: numpy==1.26.4
Requires-Dist: msgpack
Requires-Dist: robotpy_wpimath==2026.1.1b1
Requires-Dist: robotpy_apriltag==2026.1.1b1
Requires-Dist: robotpy_cscore==2026.1.1b1
Requires-Dist: robotpy_wpiutil==2026.1.1b1
Requires-Dist: wpilib==2026.1.1b1
Requires-Dist: pyntcore==2026.1.1b1
Requires-Dist: opencv_python==4.8.0.74
Requires-Dist: opencv_contrib_python==4.8.0.74
Requires-Dist: PyYAML
Requires-Dist: pathspec
Requires-Dist: paramiko
Requires-Dist: scp>=0.15.0
Requires-Dist: questionary
Requires-Dist: tqdm
Requires-Dist: toml
Requires-Dist: psutil
Requires-Dist: protobuf
Requires-Dist: betterproto==2.0.0b7
Requires-Dist: websockets
Provides-Extra: dev
Requires-Dist: wheel; extra == "dev"
Requires-Dist: setuptools; extra == "dev"
Requires-Dist: pytest; extra == "dev"
Requires-Dist: pytest-asyncio; extra == "dev"
Requires-Dist: pytest-mock; extra == "dev"
Requires-Dist: ruff; extra == "dev"
Requires-Dist: isort; extra == "dev"
Requires-Dist: pyright; extra == "dev"
Requires-Dist: build; extra == "dev"
Requires-Dist: reuse; extra == "dev"
Requires-Dist: requests; extra == "dev"
Dynamic: description
Dynamic: description-content-type
Dynamic: license-file
Dynamic: provides-extra
Dynamic: requires-dist
Dynamic: requires-python
Dynamic: summary
